Metadata-Version: 2.1
Name: distri-bution-probability
Version: 1.0
Summary: Gaussian and bionomial distributions
Home-page: UNKNOWN
Author: Marina Lovenita
Author-email: lovenita.marina@gmail.com
License: UNKNOWN
Platform: UNKNOWN
